ebm/__init__.py
ebm/__main__.py
ebm/__version__.py
ebm/energy_consumption.py
ebm/extractors.py
ebm/heating_system_forecast.py
ebm/holiday_home_energy.py
ebm/migrations.py
ebm/s_curve.py
ebm/temp_calc.py
ebm/validators.py
ebm/cmd/__init__.py
ebm/cmd/calibrate.py
ebm/cmd/calibrate_excel_com_io.py
ebm/cmd/ebmexe.py
ebm/cmd/heating_systems_by_year.py
ebm/cmd/helpers.py
ebm/cmd/initialize.py
ebm/cmd/migrate.py
ebm/cmd/pipeline.py
ebm/cmd/prepare_main.py
ebm/cmd/result_handler.py
ebm/cmd/run_calculation.py
ebm/data/calibrated/area.csv
ebm/data/calibrated/area_new_residential_buildings.csv
ebm/data/calibrated/area_per_person.csv
ebm/data/calibrated/building_code_parameters.csv
ebm/data/calibrated/calibrate_energy_consumption.csv
ebm/data/calibrated/calibrate_heating_rv.csv
ebm/data/calibrated/energy_need_behaviour_factor.csv
ebm/data/calibrated/energy_need_improvements.csv
ebm/data/calibrated/energy_need_original_condition.csv
ebm/data/calibrated/heating_system_efficiencies.csv
ebm/data/calibrated/heating_system_forecast.csv
ebm/data/calibrated/heating_system_initial_shares.csv
ebm/data/calibrated/holiday_home_energy_consumption.csv
ebm/data/calibrated/holiday_home_stock.csv
ebm/data/calibrated/improvement_building_upgrade.csv
ebm/data/calibrated/new_buildings_residential.csv
ebm/data/calibrated/population_forecast.csv
ebm/data/calibrated/s_curve.csv
ebm/data/original/area.csv
ebm/data/original/area_new_residential_buildings.csv
ebm/data/original/area_per_person.csv
ebm/data/original/building_code_parameters.csv
ebm/data/original/energy_need_behaviour_factor.csv
ebm/data/original/energy_need_improvements.csv
ebm/data/original/energy_need_original_condition.csv
ebm/data/original/heating_system_efficiencies.csv
ebm/data/original/heating_system_forecast.csv
ebm/data/original/heating_system_initial_shares.csv
ebm/data/original/holiday_home_energy_consumption.csv
ebm/data/original/holiday_home_stock.csv
ebm/data/original/improvement_building_upgrade.csv
ebm-1.0.6.dist-info/licenses/LICENSE
ebm-1.0.6.dist-info/METADATA
ebm-1.0.6.dist-info/WHEEL
ebm-1.0.6.dist-info/entry_points.txt
ebm-1.0.6.dist-info/top_level.txt
ebm-1.0.6.dist-info/RECORD
