Metadata-Version: 2.4
Name: ebm
Version: 1.0.6
Summary: EBM is a bottom-up model that forecast estimates how area, energy need, heating systems and yearly energy use in the Norwegian building stock towards 2050
Author-email: ebm@nve.no, Lars Petrusson <lfep@nve.no>, Mohammed Ettyabi <moe@nve.no>, Ketil Nordstad <kenord@nve.no>
License-Expression: MIT
Project-URL: Homepage, https://www.nve.no/
Project-URL: Documentation, https://nve.github.io/ebm-docs
Project-URL: Repository, https://github.com/NVE/ebm.git
Keywords: building energy,building model,energy use buildings,energy need buildings,building area,area,building stock,energy forecast,area forecast,norwegian buildings
Classifier: Development Status :: 3 - Alpha
Classifier: Intended Audience :: Science/Research
Classifier: Intended Audience :: Financial and Insurance Industry
Classifier: Topic :: Scientific/Engineering :: Information Analysis
Classifier: Operating System :: OS Independent
Classifier: Operating System :: Microsoft :: Windows
Classifier: Programming Language :: Python :: 3
Classifier: Programming Language :: Python :: 3.11
Classifier: Programming Language :: Python :: 3.12
Classifier: Programming Language :: Python :: 3.13
Requires-Python: >=3.11
License-File: LICENSE
Requires-Dist: loguru
Requires-Dist: numpy==2.2.6
Requires-Dist: openpyxl
Requires-Dist: pandas==2.2.3
Requires-Dist: python-dotenv
Requires-Dist: pandera==0.20.4
Requires-Dist: XlsxWriter
Requires-Dist: pywin32; platform_system == "Windows"
Requires-Dist: polars==1.31.0
Requires-Dist: pyarrow==20.0.0
Requires-Dist: azure-identity==1.23.0
Provides-Extra: test
Requires-Dist: pytest; extra == "test"
Provides-Extra: build
Requires-Dist: build; extra == "build"
Provides-Extra: dev
Requires-Dist: ebm[test]; extra == "dev"
Requires-Dist: ebm[build]; extra == "dev"
Requires-Dist: ruff; extra == "dev"
Requires-Dist: ruff-lsp; extra == "dev"
Provides-Extra: docs
Requires-Dist: sphinx; extra == "docs"
Requires-Dist: sphinx-rtd-theme; extra == "docs"
Requires-Dist: sphinx-autodoc-typehints; extra == "docs"
Requires-Dist: numpydoc; extra == "docs"
Requires-Dist: sphinx-tabs; extra == "docs"
Provides-Extra: tqdm
Requires-Dist: tqdm; extra == "tqdm"
Requires-Dist: XlsxWriter; extra == "tqdm"
Dynamic: license-file
